{
  "month": "9",
  "num": 1420,
  "link": "",
  "year": "2014",
  "news": "",
  "safeTitle": "Watches",
  "transcript": "[[A timeline runs across the top with notches at 1990, 2000, 2010, 2020, and 2030. Below it, a shaded box that reads \u0027Regular Watches\u0027 runs from the far left to about 2003. Another shaded box, from about 2015 to the far right, reads \u0027Smart Watches\u0027. An arrow points to the blank space between them.]]\nBrief, glorious period in which our wrists were free\n\n{{Title text: Old people used to write obnoxious thinkpieces about how people these days always wear watches and are slaves to the clock, but now they\u0027ve switched to writing thinkpieces about how kids these days don\u0027t appreciate the benefits of an old-fashioned watch. My position is: The word \u0027thinkpiece\u0027 sounds like a word made up by someone who didn\u0027t know about the word \u0027brain\u0027.}}",
  "alt": "Old people used to write obnoxious thinkpieces about how people these days always wear watches and are slaves to the clock, but now they\u0027ve switched to writing thinkpieces about how kids these days don\u0027t appreciate the benefits of an old-fashioned watch. My position is: The word \u0027thinkpiece\u0027 sounds like a word made up by someone who didn\u0027t know about the word \u0027brain\u0027.",
  "img": "1420/watches.png",
  "title": "Watches",
  "day": "12",
  "baseUri": "https://dylanlangston.github.io/Axkcd/"
}