{
  "month": "11",
  "num": 337,
  "link": "",
  "year": "2007",
  "news": "",
  "safeTitle": "Post Office Showdown",
  "transcript": "I spend a lot of time mentally choreographing elaborate fight scenes with strangers around me.\n[[Man is in a post office wearing earphones.  There are several other people, including an old man with a crutch and an old woman with a long narrow box]]\nMan\u0027s thoughts: Okay - if that old man pulls a crossbow,\nMan\u0027s thoughts: I\u0027ll throw the postal scale at him and dive backward behind the stamps machine.\nMan\u0027s thoughts: But what if the lady by the door has a katana in that box?\nMan\u0027s thoughts: Better set my iPod to the \u0022Kill Bill\u0022 fight theme, just in case.\n{{alt text: That track (\u0027Battle Without Honor or Humanity\u0027) -- like \u0027Ride of the Valkyries\u0027 -- improves *any* activity.}}",
  "alt": "That track (\u0027Battle Without Honor or Humanity\u0027) -- like \u0027Ride of the Valkyries\u0027 -- improves *any* activity.",
  "img": "337/post_office_showdown.png",
  "title": "Post Office Showdown",
  "day": "2",
  "baseUri": "https://example.com/"
}