{
  "month": "7",
  "num": 1867,
  "link": "",
  "year": "2017",
  "news": "",
  "safeTitle": "Physics Confession",
  "transcript": "",
  "alt": "\u0022You know lightning, right? When electric charge builds up in a cloud and then discharges in a giant spark? Ask me why that happens.\u0022 \u0022Why does tha--\u0022 \u0022No clue. We think it\u0027s related to the hair thing.\u0022",
  "img": "1867/physics_confession.png",
  "title": "Physics Confession",
  "day": "24",
  "baseUri": "https://dylanlangston.github.io/Axkcd/"
}