{
  "month": "11",
  "num": 1285,
  "link": "",
  "year": "2013",
  "news": "",
  "safeTitle": "Third Way",
  "transcript": "[[Two groups stand, with placards and weapons, angrily facing off against each other. The first group, with a cutlass, has a sign reading \u0022TWO spaces after a period\u0022. The second group, with a spear, has a sign reading \u0022ONE space after a period.\u0022 Off to one side stands a figure, alone, with a placard reading \u0022Line break after every sentence.\u0022]]\n\n{{Title text: \u0027The monospaced-typewriter-font story is a COMPLETE FABRICATION!  WAKE UP, SHEEPLE\u0027 \u0027It doesn\u0027t matter! Studies support single spaces!\u0027 \u0027Those results weren\u0027t statistically significant!\u0027 \u0027Fine, you win. I\u0027m using double spaces right now!\u0027 \u0027Are not!  We can all hear your stupid whitespace.\u0027}}",
  "alt": "\u0027The monospaced-typewriter-font story is a COMPLETE FABRICATION!  WAKE UP, SHEEPLE\u0027 \u0027It doesn\u0027t matter! Studies support single spaces!\u0027 \u0027Those results weren\u0027t statistically significant!\u0027 \u0027Fine, you win. I\u0027m using double spaces right now!\u0027 \u0027Are not!  We can all hear your stupid whitespace.\u0027",
  "img": "1285/third_way.png",
  "title": "Third Way",
  "day": "1",
  "baseUri": "https://example.com/"
}