{
  "month": "4",
  "num": 91,
  "link": "",
  "year": "2006",
  "news": "",
  "safeTitle": "Pwned",
  "transcript": "[[Text only panel, hand written.]]\nWelcome to text-only Counterstrike.\nYou are in a dark, outdoor map.\n\u003E GO NORTH\nYou have been pwned by a grue.",
  "alt": "I\u0027m sure a discussion of the reason for the disappearance of adventure games in favor of RPGs would be fascinating",
  "img": "91/pwned.png",
  "title": "Pwned",
  "day": "19",
  "baseUri": "https://dylanlangston.github.io/Axkcd/"
}