{
  "month": "4",
  "num": 1203,
  "link": "",
  "year": "2013",
  "news": "",
  "safeTitle": "Time Machines",
  "transcript": "The Problem With Time Machines:\n[[Character stands holding the lever of a box labeled \u0022Time Machine,\u0022 with a big on\noff lever switched to off.]]\n\n[[He flips it on.]]\n\u003C\u003Cclick\u003E\u003E\neeeeEEEEEEEE\n\nEEEEEEEEeeee\n\u003C\u003Cclick\u003E\u003E\n[[He flips it off.]]\n\n[[He stares at his own hands in confusion.]]\n???\n\n{{Title text: \u0027All time machine systems nominal ... T-minus ten ... eleven ...\u0027}}",
  "alt": "\u0027All time machine systems nominal ... T-minus ten ... eleven ...\u0027",
  "img": "1203/time_machines.png",
  "title": "Time Machines",
  "day": "24",
  "baseUri": "https://dylanlangston.github.io/Axkcd/"
}