{
  "month": "6",
  "num": 913,
  "link": "",
  "year": "2011",
  "news": "",
  "safeTitle": "Core",
  "transcript": "[[A cutaway diagram of the Earth, with colored layers including a labeled outer core and inner core.]]\n\n[[A closeup of the stylized outer core, labeled \u0022Turbulent molten metals at 30 million PSI\u0022 with turbulence lines, and of the inner core, labeled \u0022moon-sized iron sphere.\u0022]]\n\n[[Person reading a book pulls legs up tight under office chair, peering downwards.]]\n\nI freak out about fifteen minutes into reading anything about the Earth\u0027s core when I suddenly realize it\u0027s RIGHT UNDER ME.\n\n{{Title text: If you\u0027re a geologist or geophysicist and you don\u0027t introduce yourself by saying your name, then gesturing downward and saying \u0022... and I study that\u0022, I don\u0027t know what you\u0027re doing with your life.}}",
  "alt": "If you\u0027re a geologist or geophysicist and you don\u0027t introduce yourself by saying your name, then gesturing downward and saying \u0022... and I study that\u0022, I don\u0027t know what you\u0027re doing with your life.",
  "img": "913/core.png",
  "title": "Core",
  "day": "17",
  "baseUri": "https://dylanlangston.github.io/Axkcd/"
}