{
  "month": "6",
  "num": 1067,
  "link": "",
  "year": "2012",
  "news": "",
  "safeTitle": "Pressures",
  "transcript": "[[A person walks up to a patent clerk examining documents]]\nPerson: So.. what\u0027ve you been up to?\nPatent Clerk: Handling patent applications.\nPerson: Yeah, but... besides that?\nPatent Clerk: That\u0027s about it.\nPerson: You\u0027re not, like, thinking about any cool stuff? Just curious.\nFor the last hundred years, Swiss patent clerks have been under some weird pressures.\n\n{{Title text: Everyone\u0027s caught by surprise when a theory of quantum gravity is developed by a sound technician wearing patent leather shoes while editing Clerks II.}}",
  "alt": "Everyone\u0027s caught by surprise when a theory of quantum gravity is developed by a sound technician wearing patent leather shoes while editing Clerks II.",
  "img": "1067/pressures.png",
  "title": "Pressures",
  "day": "11",
  "baseUri": "https://example.com/"
}